Workbook

Sheet Summary
A1: Inventory analysis: summary
A3: Products | B3: =COUNTA(Products!A2:A41)
A4: Total units sold | B4: =SUM(Products!G2:G41)
A5: Total revenue | B5: =SUM(Products!H2:H41)
A6: Total profit | B6: =SUM(Products!I2:I41)
A7: Profit margin | B7: =B6/B5
A8: Revenue from class A products | B8: ='By class'!E2
A9: Total cost, policy 1 (average demand) | B9: =Policies!G4
A10: Total cost, policy 2 (seasonal forecast) | B10: =Policies!G5
A11: Total cost, policy 3 (forecast + safety stock) | B11: =Policies!G6

Sheet Products
A1: Product | B1: Category | C1: Class | D1: Unit cost | E1: Unit price | F1: Lead time (weeks) | G1: Units sold | H1: Revenue | I1: Profit | J1: Safety stock (units)
A2: P22 | B2: Office | C2: A | D2: 67.45 | E2: 95.1 | F2: 1 | G2: 23764 | H2: =G2*E2 | I2: =G2*(E2-D2) | J2: 302
A3: P21 | B3: Garden | C3: A | D3: 37.79 | E3: 55.65 | F3: 4 | G3: 9893 | H3: =G3*E3 | I3: =G3*(E3-D3) | J3: 257
A4: P38 | B4: Kitchen | C4: A | D4: 47.66 | E4: 67.48 | F4: 3 | G4: 8788 | H4: =G4*E4 | I4: =G4*(E4-D4) | J4: 146
A5: P01 | B5: Home | C5: A | D5: 61.86 | E5: 86.56 | F5: 2 | G5: 7277 | H5: =G5*E5 | I5: =G5*(E5-D5) | J5: 105
A6: P09 | B6: Home | C6: A | D6: 16.57 | E6: 20.69 | F6: 3 | G6: 6228 | H6: =G6*E6 | I6: =G6*(E6-D6) | J6: 114
A7: P06 | B7: Kitchen | C7: A | D7: 19.6 | E7: 24.05 | F7: 3 | G7: 5842 | H7: =G7*E7 | I7: =G7*(E7-D7) | J7: 110
A8: P31 | B8: Office | C8: B | D8: 19.99 | E8: 26.72 | F8: 4 | G8: 4377 | H8: =G8*E8 | I8: =G8*(E8-D8) | J8: 68
A9: P40 | B9: Garden | C9: B | D9: 13.59 | E9: 18.87 | F9: 4 | G9: 4173 | H9: =G9*E9 | I9: =G9*(E9-D9) | J9: 78
A10: P07 | B10: Home | C10: A | D10: 40 | E10: 56.67 | F10: 1 | G10: 3632 | H10: =G10*E10 | I10: =G10*(E10-D10) | J10: 46
A11: P20 | B11: Office | C11: A | D11: 55.24 | E11: 82.23 | F11: 2 | G11: 3583 | H11: =G11*E11 | I11: =G11*(E11-D11) | J11: 61
A12: P15 | B12: Garden | C12: A | D12: 40.22 | E12: 51.9 | F12: 4 | G12: 3080 | H12: =G12*E12 | I12: =G12*(E12-D12) | J12: 72
A13: P23 | B13: Home | C13: A | D13: 57.52 | E13: 73.61 | F13: 2 | G13: 2488 | H13: =G13*E13 | I13: =G13*(E13-D13) | J13: 38
... A41: P25 | B41: Kitchen | C41: C | D41: 67.42 | E41: 96.66 | F41: 4 | G41: 273 | H41: =G41*E41 | I41: =G41*(E41-D41) | J41: 4

Sheet Policies
A1: Holding cost (share of stock value per year) | B1: 0.2
A2: Blue/yellow cell = assumption. Change it and the costs below recalculate.
A3: Policy | B3: Lost revenue | C3: Stock value | D3: Fill rate % | E3: Lost profit | F3: Holding cost | G3: Total cost
A4: 1. Average demand, no safety stock (Lesson 3) | B4: 100622 | C4: 109683 | D4: 98.2 | E4: 28634 | F4: =C4*$B$1 | G4: =E4+F4
A5: 2. Seasonal forecast, no safety stock | B5: 14429 | C5: 98394 | D5: 99.8 | E5: 4167 | F5: =C5*$B$1 | G5: =E5+F5
A6: 3. Seasonal forecast + safety stock by class | B6: 53 | C6: 180519 | D6: 100 | E6: 13 | F6: =C6*$B$1 | G6: =E6+F6
A8: Lost profit = lost units x (price - cost). Holding cost = average stock value x holding rate.

Sheet By class
A1: Class | B1: Products | C1: Units sold | D1: Revenue | E1: Share of revenue | F1: Safety stock (units)
A2: A | B2: =COUNTIF(Products!$C$2:$C$41,A2) | C2: =SUMIFS(Products!$G$2:$G$41,Products!$C$2:$C$41,A2) | D2: =SUMIFS(Products!$H$2:$H$41,Products!$C$2:$C$41,A2) | E2: =IFERROR(D2/$D$5,0) | F2: =SUMIFS(Products!$J$2:$J$41,Products!$C$2:$C$41,A2)
A3: B | B3: =COUNTIF(Products!$C$2:$C$41,A3) | C3: =SUMIFS(Products!$G$2:$G$41,Products!$C$2:$C$41,A3) | D3: =SUMIFS(Products!$H$2:$H$41,Products!$C$2:$C$41,A3) | E3: =IFERROR(D3/$D$5,0) | F3: =SUMIFS(Products!$J$2:$J$41,Products!$C$2:$C$41,A3)
A4: C | B4: =COUNTIF(Products!$C$2:$C$41,A4) | C4: =SUMIFS(Products!$G$2:$G$41,Products!$C$2:$C$41,A4) | D4: =SUMIFS(Products!$H$2:$H$41,Products!$C$2:$C$41,A4) | E4: =IFERROR(D4/$D$5,0) | F4: =SUMIFS(Products!$J$2:$J$41,Products!$C$2:$C$41,A4)
A5: Total | B5: =SUM(B2:B4) | C5: =SUM(C2:C4) | D5: =SUM(D2:D4) | E5: =SUM(E2:E4) | F5: =SUM(F2:F4)

Sheet Weekly demand
A1: Week | B1: Garden | C1: Home | D1: Kitchen | E1: Office
A2: 1 | B2: 366 | C2: 465 | D2: 347 | E2: 860
A3: 2 | B3: 272 | C3: 387 | D3: 414 | E3: 861
A4: 3 | B4: 321 | C4: 436 | D4: 440 | E4: 705
A5: 4 | B5: 321 | C5: 458 | D5: 410 | E5: 765
A6: 5 | B6: 407 | C6: 547 | D6: 400 | E6: 666
A7: 6 | B7: 375 | C7: 483 | D7: 402 | E7: 744
A8: 7 | B8: 393 | C8: 392 | D8: 409 | E8: 887
A9: 8 | B9: 448 | C9: 389 | D9: 480 | E9: 764
A10: 9 | B10: 439 | C10: 489 | D10: 486 | E10: 996
A11: 10 | B11: 441 | C11: 537 | D11: 533 | E11: 723
A12: 11 | B12: 634 | C12: 508 | D12: 462 | E12: 904
A13: 12 | B13: 586 | C13: 599 | D13: 551 | E13: 793
... A53: 52 | B53: 225 | C53: 408 | D53: 365 | E53: 576
